shapes_recognition/.DS_Store
shapes_recognition/__init__.py
shapes_recognition/src/.DS_Store
shapes_recognition/src/cfg.py
shapes_recognition/src/create_joint_table.py
shapes_recognition/src/create_table.py
shapes_recognition/src/create_template.py
shapes_recognition/src/get_column_data.py
shapes_recognition/src/get_peaks.py
shapes_recognition/src/get_results.py
shapes_recognition/src/recognition.py
shapes_recognition/src/save_results.py
shapes_recognition/src/self_study.py
shapes_recognition/src/set_method.py
shapes_recognition/src/show_results.py
shapes_recognition/src/to_canonical.py
shapes_recognition/src/utils.py
shapes_recognition-3.2.0.dist-info/METADATA
shapes_recognition-3.2.0.dist-info/WHEEL
shapes_recognition-3.2.0.dist-info/RECORD
