Metadata-Version: 2.1
Name: shapes-recognition
Version: 3.2.0
Summary: "shapes-recognition" is a test for a new recognition technology
License: MIT
Author: Boris Kravtsov
Author-email: kravtsov.development@gmail.com
Requires-Python: >=3.11,<4.0
Classifier: License :: OSI Approved :: MIT License
Classifier: Programming Language :: Python :: 3
Classifier: Programming Language :: Python :: 3.11
Requires-Dist: opencv-python-headless (>=4.8.1.78,<5.0.0.0)
Requires-Dist: pnt2 (>=1.0.3,<2.0.0)
Requires-Dist: pnt3 (>=1.0.3,<2.0.0)
Requires-Dist: tqdm (>=4.66.1,<5.0.0)
